djstartlib/__init__.py
djstartlib/main.py
djstartlib/version.py
djstartlib/models/__init__.py
djstartlib/models/app_manager.py
djstartlib/models/djstart_interface.py
djstartlib/models/project_manager.py
djstartlib/models/utils/__init__.py
djstartlib/models/utils/environment.py
djstartlib/models/utils/hellper.py
django_start_automate-1.1.6.dist-info/LICENSE
django_start_automate-1.1.6.dist-info/METADATA
django_start_automate-1.1.6.dist-info/WHEEL
django_start_automate-1.1.6.dist-info/entry_points.txt
django_start_automate-1.1.6.dist-info/top_level.txt
django_start_automate-1.1.6.dist-info/RECORD
