Metadata-Version: 2.1
Name: django-start-automate
Version: 1.1.6
Summary: Prepare a new Django project quickly and automatically and more wonderful things that save you time By django start
Home-page: https://github.com/islam-kamel/django-start
Author: Islam Kamel
Author-email: islam.kamel@agr.svu.edu.eg
License: MIT
Keywords: django-start,django start,djngo start,django start project,django project,django automate,automate django,start,start automate,django build,django tools,automate start,djangostart,django_start,django-start-automate,django_start_automate,django start automate,django script,django cli,django tool,python cli,python tool,python tools,python script
Classifier: Development Status :: 4 - Beta
Classifier: License :: OSI Approved :: MIT License
Classifier: Environment :: Console
Classifier: Intended Audience :: Developers
Classifier: Operating System :: OS Independent
Classifier: Programming Language :: Python :: 3
Classifier: Programming Language :: Python :: 3 :: Only
Classifier: Programming Language :: Python :: 3.7
Classifier: Programming Language :: Python :: 3.8
Classifier: Programming Language :: Python :: 3.9
Classifier: Programming Language :: Python :: 3.10
Classifier: Programming Language :: Python :: 3.11
Classifier: Programming Language :: Python :: Implementation :: CPython
Classifier: Framework :: Django
Classifier: Framework :: Django :: 3
Classifier: Framework :: Django :: 3.0
Classifier: Framework :: Django :: 3.1
Classifier: Framework :: Django :: 3.2
Classifier: Framework :: Django :: 4
Classifier: Framework :: Django :: 4.0
Classifier: Framework :: Django :: 4.1
Classifier: Topic :: Software Development :: Build Tools
Classifier: Topic :: Software Development :: Code Generators
Classifier: Topic :: Terminals
Classifier: Topic :: Software Development :: Libraries :: Python Modules
Requires-Python: >=3.7
License-File: LICENSE
Requires-Dist: click
